cbdep/__init__.py
cbdep/cache.py
cbdep/cbdep.config
cbdep/cli.py
cbdep/install.py
cbdep/platform_introspection.py
cbdep/zipfile_with_permissions.py
cbdep-1.3.10.dist-info/entry_points.txt
cbdep-1.3.10.dist-info/LICENSE.txt
cbdep-1.3.10.dist-info/WHEEL
cbdep-1.3.10.dist-info/METADATA
cbdep-1.3.10.dist-info/RECORD
