Metadata-Version: 2.3
Name: cbdep
Version: 1.3.10
Summary: Generalized tool installer
Author-email: Couchbase Build Team <build-team@couchbase.com>
Requires-Python: >=3.10
Classifier: Development Status :: 4 - Beta
Classifier: Environment :: Console
Classifier: Intended Audience :: Developers
Classifier: License :: OSI Approved
Classifier: Operating System :: MacOS :: MacOS X
Classifier: Operating System :: POSIX
Requires-Dist: PyYAML
Requires-Dist: distro
Requires-Dist: requests
Requires-Dist: packaging
